[{"main":"BT","department":"财务部","fee":116364.02,"month":202203},{"main":"BT","department":"总裁办","fee":0.0,"month":202203},{"main":"BT","department":"人事行政部","fee":229494.89,"month":202203},{"main":"BT","department":"发行部","fee":57601.98,"month":202203},{"main":"BT","department":"中台研发部","fee":102148.95,"month":202203},{"main":"BT","department":"市场投放组","fee":243543.38,"month":202203},{"main":"BT","department":"市场素材组","fee":355404.99,"month":202203},{"main":"BT","department":"中台美术部","fee":143967.77,"month":202203},{"main":"BT","department":"A1项目","fee":515794.59,"month":202203},{"main":"BT","department":"A2项目","fee":279123.96,"month":202203},{"main":"BT","department":"A3项目","fee":56041.16,"month":202203},{"main":"BT","department":"A项目美术","fee":180044.39,"month":202203},{"main":"BT","department":"A项目程序","fee":19635.48,"month":202203},{"main":"BT","department":"中台测试部","fee":33299.65,"month":202203},{"main":"BT","department":"H1项目","fee":153803.02,"month":202203},{"main":"DL","department":"H2项目","fee":296790.13,"month":202203},{"main":"CT","department":"人事行政部","fee":57101.85,"month":202203},{"main":"CT","department":"市场部","fee":22262.05,"month":202203},{"main":"CT","department":"美术中台部","fee":51318.9,"month":202203},{"main":"CT","department":"T1项目","fee":75801.15,"month":202203},{"main":"CT","department":"T2项目","fee":115692.67,"month":202203},{"main":"CT","department":"T项目美术","fee":32441.63,"month":202203},{"main":"CT","department":"研发中台部","fee":87575.28,"month":202203}]